mcd_regression/__init__.py
mcd_regression/_version.py
mcd_regression/mcdr.py
mcd_regression-0.1.1.dist-info/licenses/LICENSE
mcd_regression-0.1.1.dist-info/METADATA
mcd_regression-0.1.1.dist-info/WHEEL
mcd_regression-0.1.1.dist-info/top_level.txt
mcd_regression-0.1.1.dist-info/RECORD
