Metadata-Version: 2.4
Name: mcd-regression
Version: 0.1.1
Summary: Robust linear regression in the multiple regression and multivariate regression cases using the minimum covariance determinant (MCD).
Author-email: Steven Stetzler <steven.stetzler@gmail.com>
License: MIT License
Project-URL: Source Code, https://github.com/stevenstetzler/mcd-regression
Classifier: Development Status :: 4 - Beta
Classifier: License :: OSI Approved :: MIT License
Classifier: Intended Audience :: Developers
Classifier: Intended Audience :: Science/Research
Classifier: Operating System :: OS Independent
Classifier: Programming Language :: Python
Requires-Python: >=3.9
License-File: LICENSE
Requires-Dist: numpy
Requires-Dist: scipy
Requires-Dist: scikit-learn
Provides-Extra: dev
Requires-Dist: matplotlib; extra == "dev"
Dynamic: license-file
